airulefy/__init__.py
airulefy/__main__.py
airulefy/config.py
airulefy/fsutils.py
airulefy/generator/__init__.py
airulefy/generator/base.py
airulefy/generator/cline.py
airulefy/generator/copilot.py
airulefy/generator/cursor.py
airulefy/generator/devin.py
airulefy/watcher.py
airulefy-0.1.3.dist-info/LICENSE
airulefy-0.1.3.dist-info/METADATA
airulefy-0.1.3.dist-info/WHEEL
airulefy-0.1.3.dist-info/entry_points.txt
airulefy-0.1.3.dist-info/RECORD
